{
    "defaultSearch": [
        {
            "baseUrl": "https://www.indeed.com/jobs?"
        },
        {
            "jobTitle": "q=spanish+teacher"
        },
        {
            "location": "l=new+york"
        },
        {
            "salary": null
        },
        {
            "postsSince": "fromage=3"
        },
        {
            "sort": "sort=date"
        },
        {
            "viewJobUrl": "https://www.indeed.com/viewjob?jk="
        },
        {
            "searchTitle": "Spanish teacher"
        }
    ]
}